{
  "date": "2024-12-27",
  "date_range": {
    "start": "2024-12-21",
    "end": "2024-12-27"
  },
  "generated_at": "2026-05-18T13:31:35.916483Z",
  "highlights": [
    {
      "rank": 1,
      "type": "top_event",
      "event_id": "makino-2024-12-27-139",
      "date": "2024-12-27",
      "title": "Japan's Nidec takes aim at Makino Milling with $1.6 bln unsolicited bid - Reuters",
      "importance_score": 0.5
    }
  ],
  "anomalies_7d": [],
  "topic_7d_summary": {
    "automation_capex": {
      "this_week": 1,
      "last_week": 0,
      "week_over_week_change": "N/A",
      "sentiment_this_week": 0.0
    }
  },
  "company_7d_summary": {
    "makino": {
      "event_count": 1,
      "sentiment_avg": 0.0,
      "rank": 1
    }
  },
  "comparisons": {
    "vs_last_week": {
      "event_count": {
        "this": 1,
        "last": 0,
        "change_pct": 0
      }
    }
  },
  "daily_breakdown": [
    {
      "date": "2024-12-21",
      "event_count": 0,
      "sentiment_avg": 0.0
    },
    {
      "date": "2024-12-22",
      "event_count": 0,
      "sentiment_avg": 0.0
    },
    {
      "date": "2024-12-23",
      "event_count": 0,
      "sentiment_avg": 0.0
    },
    {
      "date": "2024-12-24",
      "event_count": 0,
      "sentiment_avg": 0.0
    },
    {
      "date": "2024-12-25",
      "event_count": 0,
      "sentiment_avg": 0.0
    },
    {
      "date": "2024-12-26",
      "event_count": 0,
      "sentiment_avg": 0.0
    },
    {
      "date": "2024-12-27",
      "event_count": 1,
      "sentiment_avg": 0.0
    }
  ]
}