{
  "date": "2026-02-09",
  "generated_at": "2026-05-03T02:41:20.126776Z",
  "top_events": [
    {
      "rank": 1,
      "event_id": "unknown-2026-02-09-005",
      "importance_score": 0.75,
      "importance_reasons": [
        "涉及財報"
      ],
      "title": "11 reasons robots struggle to scale in high-mix manufacturing - The Robot Report",
      "companies": [],
      "related": {
        "customers": [],
        "suppliers": []
      },
      "topics": [
        "automation_capex",
        "earnings"
      ],
      "sentiment": {
        "label": "neutral",
        "score": 0.0
      },
      "source_url": null
    },
    {
      "rank": 2,
      "event_id": "hiwin-2026-02-09-004",
      "importance_score": 0.75,
      "importance_reasons": [
        "涉及財報"
      ],
      "title": "Taiwan’s Hiwin expects revenue growth on rising machine tool orders - Taiwan News",
      "companies": [
        "hiwin"
      ],
      "related": {
        "customers": [],
        "suppliers": []
      },
      "topics": [
        "machine_tool_orders",
        "earnings"
      ],
      "sentiment": {
        "label": "positive",
        "score": 0.5
      },
      "source_url": null
    }
  ],
  "anomalies": [],
  "topic_trends": {
    "automation_capex": {
      "today": 1,
      "7d_avg": 0,
      "30d_avg": 0,
      "yoy_same_week": null,
      "trend": "new",
      "consecutive_weeks_rising": 0,
      "sentiment_today": 0.0,
      "sentiment_7d_avg": null
    },
    "earnings": {
      "today": 2,
      "7d_avg": 0,
      "30d_avg": 0,
      "yoy_same_week": null,
      "trend": "new",
      "consecutive_weeks_rising": 0,
      "sentiment_today": 0.25,
      "sentiment_7d_avg": null
    },
    "machine_tool_orders": {
      "today": 1,
      "7d_avg": 0,
      "30d_avg": 0,
      "yoy_same_week": null,
      "trend": "new",
      "consecutive_weeks_rising": 0,
      "sentiment_today": 0.5,
      "sentiment_7d_avg": null
    }
  },
  "supply_chain_activity": [],
  "stats": {
    "total_events": 2,
    "sentiment_distribution": {
      "positive": 1,
      "neutral": 1,
      "negative": 0
    },
    "top_companies": [
      {
        "id": "hiwin",
        "count": 1
      }
    ],
    "top_topics": [
      {
        "id": "earnings",
        "count": 2
      },
      {
        "id": "automation_capex",
        "count": 1
      },
      {
        "id": "machine_tool_orders",
        "count": 1
      }
    ]
  }
}