{
  "date": "2026-05-13",
  "total_events": 10,
  "by_company": {
    "delta": {
      "count": 1,
      "sentiment_avg": 0.0
    },
    "abb": {
      "count": 1,
      "sentiment_avg": 0.0
    },
    "mitsubishi_electric": {
      "count": 3,
      "sentiment_avg": 0.0
    },
    "itw": {
      "count": 1,
      "sentiment_avg": 0.0
    },
    "caterpillar": {
      "count": 2,
      "sentiment_avg": 0.0
    }
  },
  "by_topic": {
    "automation_capex": {
      "count": 9,
      "sentiment_avg": 0.0
    },
    "industry_general": {
      "count": 7,
      "sentiment_avg": 0.0
    },
    "earnings": {
      "count": 6,
      "sentiment_avg": 0.0
    },
    "guidance": {
      "count": 2,
      "sentiment_avg": 0.0
    }
  },
  "baselines_used": {
    "companies": {},
    "topics": {}
  },
  "supply_chain_activity": []
}